namu/__init__.py
namu/main.py
namu/namu.py
namu/strings_with_arrows.py
namu-0.0.4.2.dist-info/LICENSE
namu-0.0.4.2.dist-info/METADATA
namu-0.0.4.2.dist-info/WHEEL
namu-0.0.4.2.dist-info/top_level.txt
namu-0.0.4.2.dist-info/RECORD
