Metadata-Version: 2.1
Name: namu
Version: 0.0.4.2
Summary: 한글 프로그래밍 언어 '나무'를 실행할 수 있는 패키지입니다.
Home-page: https://repl.it/@prnm789/namupackage
Author: prnm789
Author-email: prnm789@gmail.com
License: UNKNOWN
Platform: UNKNOWN
Classifier: Programming Language :: Python :: 3
Classifier: License :: OSI Approved :: MIT License
Classifier: Operating System :: OS Independent
Requires-Python: >=3.6
